ngbs_icon/__init__.py
ngbs_icon/api.py
ngbs_icon/exceptions.py
ngbs_icon/models.py
ngbs_icon/transport.py
ngbs_icon-0.2.0.dist-info/licenses/LICENSE
ngbs_icon-0.2.0.dist-info/METADATA
ngbs_icon-0.2.0.dist-info/WHEEL
ngbs_icon-0.2.0.dist-info/top_level.txt
ngbs_icon-0.2.0.dist-info/RECORD
