Metadata-Version: 2.4
Name: ngbs-icon
Version: 0.2.0
Summary: Async Python client for NGBS iCON controllers
Author: Your Name
License: MIT
Project-URL: Homepage, https://github.com/yourname/ngbs-icon
Requires-Python: >=3.10
License-File: LICENSE
Dynamic: license-file
